tello/__init__.py
tello/commands.py
tello/missionpads.py
tello-1.2.dist-info/LICENSE
tello-1.2.dist-info/METADATA
tello-1.2.dist-info/WHEEL
tello-1.2.dist-info/top_level.txt
tello-1.2.dist-info/RECORD
