Metadata-Version: 2.1
Name: tello
Version: 1.2
Summary: This simple Library should help you controlling the TELLO EDU over WiFi with Python.
Home-page: https://github.com/gheinzer/python-tello
Author: Gabriel Heinzer
Author-email: dev@gabrielheinzer.ch
License: UNKNOWN
Platform: UNKNOWN
Requires-Python: >=3.0
